{
  "$schema": "https://static.modelcontextprotocol.io/schemas/2025-12-11/server.schema.json",
  "name": "io.github.CSOAI-ORG/iso-42005-impact-mcp",
  "version": "1.0.4",
  "description": "ISO/IEC 42005:2025 AI Impact Assessment MCP — first international standard for AI impact",
  "repository": {
    "url": "https://github.com/CSOAI-ORG/iso-42005-impact-mcp",
    "source": "github"
  },
  "packages": [
    {
      "registryType": "pypi",
      "identifier": "iso-42005-impact-mcp",
      "version": "1.0.4",
      "runtimeHint": "python",
      "transport": {
        "type": "stdio"
      }
    }
  ],
  "remotes": [
    {
      "type": "streamable-http",
      "url": "https://api.meok.ai/v1/governance/iso-42005-impact"
    }
  ]
}
